vanadium/__init__.py
vanadium/vanadium.py
vanadium-0.0.2.4.dist-info/LICENSE
vanadium-0.0.2.4.dist-info/METADATA
vanadium-0.0.2.4.dist-info/WHEEL
vanadium-0.0.2.4.dist-info/top_level.txt
vanadium-0.0.2.4.dist-info/RECORD
