Metadata-Version: 2.1
Name: vanadium
Version: 0.0.2.4
Summary: A python module for small things; so you don't have to reinvent the wheel
Home-page: https://github.com/Cyclip/Vanadium
Author: Cyclip
Author-email: gdneop@gmail.com
License: UNKNOWN
Platform: UNKNOWN
Classifier: Programming Language :: Python :: 3
Classifier: License :: OSI Approved :: MIT License
Classifier: Operating System :: OS Independent
